geniushub/__init__.py
geniushub/geniushub.py
geniushub-0.1.dist-info/LICENSE
geniushub-0.1.dist-info/METADATA
geniushub-0.1.dist-info/WHEEL
geniushub-0.1.dist-info/top_level.txt
geniushub-0.1.dist-info/RECORD
