Metadata-Version: 2.1
Name: geniushub
Version: 0.1
Summary: Python library to provide connect to Genius Hub on a local network.
Home-page: https://github.com/GeoffAtHome/geniushub
Author: Geoff Soord
Author-email: geoff@soord.org.uk
License: MIT
Keywords: Genius,Genius Hub,Heat Genius,Heat Genius Hub
Platform: UNKNOWN
